sphinxcontrib_reviewbuilder-0.0.6-py2.7-nspkg.pth
sphinxcontrib/reviewbuilder/__init__.py
sphinxcontrib/reviewbuilder/reviewbuilder.py
sphinxcontrib/reviewbuilder/writer.py
sphinxcontrib_reviewbuilder-0.0.6.dist-info/DESCRIPTION.rst
sphinxcontrib_reviewbuilder-0.0.6.dist-info/METADATA
sphinxcontrib_reviewbuilder-0.0.6.dist-info/metadata.json
sphinxcontrib_reviewbuilder-0.0.6.dist-info/namespace_packages.txt
sphinxcontrib_reviewbuilder-0.0.6.dist-info/RECORD
sphinxcontrib_reviewbuilder-0.0.6.dist-info/top_level.txt
sphinxcontrib_reviewbuilder-0.0.6.dist-info/WHEEL
