Metadata-Version: 2.0
Name: sphinxcontrib-reviewbuilder
Version: 0.0.6
Summary: Sphinx reviewbuilder extension
Home-page: http://github.com/shirou/sphinxcontrib-reviewbuilder
Author: WAKAYAMA Shirou
Author-email: shirou.faw@gmail.com
License: LGPL
Download-URL: http://pypi.python.org/pypi/sphinxcontrib-reviewbuilder
Platform: any
Classifier: Development Status :: 4 - Beta
Classifier: Environment :: Console
Classifier: Environment :: Web Environment
Classifier: Intended Audience :: Developers
Classifier: License :: OSI Approved :: GNU Lesser General Public License v2 (LGPLv2)
Classifier: Operating System :: OS Independent
Classifier: Programming Language :: Python
Classifier: Topic :: Documentation
Classifier: Topic :: Utilities
Requires-Dist: Sphinx (>=1.2)
Requires-Dist: setuptools
